setup.cfg
setup.py
pyttern/__init__.py
pyttern/fsm.py
pyttern.egg-info/PKG-INFO
pyttern.egg-info/SOURCES.txt
pyttern.egg-info/dependency_links.txt
pyttern.egg-info/not-zip-safe
pyttern.egg-info/top_level.txt