Metadata-Version: 1.1
Name: pyttern
Version: 0.0.2dev
Summary: common pattern for python
Home-page: https://github.com/yangtianhang/pyttern
Author: yangtianhang
Author-email: tianhang.yang@gmail.com
License: MIT
Download-URL: https://github.com/yangtianhang/pyttern/tarball/0.0.2
Keywords: pattern,fsm
Platform: UNKNOWN
